<?xml version="1.0" ?>
<parts>
	<part>
		<name>0</name>
		<description>0</description>
		<color>#0b129a</color>
		<annotation>
			<vertex>
				<x>604.0</x>
				<y>432.0</y>
			</vertex>
			<vertex>
				<x>585.0</x>
				<y>523.0</y>
			</vertex>
			<vertex>
				<x>419.0</x>
				<y>491.0</y>
			</vertex>
			<vertex>
				<x>448.0</x>
				<y>407.0</y>
			</vertex>
			<vertex>
				<x>614.0</x>
				<y>414.0</y>
			</vertex>
			<vertex>
				<x>605.0</x>
				<y>434.0</y>
			</vertex>
		</annotation>
		<center>
			<x>605.0</x>
			<y>434.0</y>
		</center>
	</part>
	<part>
		<name>1</name>
		<description>1</description>
		<color>#f5759a</color>
		<annotation>
			<vertex>
				<x>472.0</x>
				<y>409.0</y>
			</vertex>
			<vertex>
				<x>447.0</x>
				<y>495.0</y>
			</vertex>
			<vertex>
				<x>272.0</x>
				<y>449.0</y>
			</vertex>
			<vertex>
				<x>262.0</x>
				<y>377.0</y>
			</vertex>
			<vertex>
				<x>375.0</x>
				<y>344.0</y>
			</vertex>
			<vertex>
				<x>465.0</x>
				<y>395.0</y>
			</vertex>
			<vertex>
				<x>470.0</x>
				<y>416.0</y>
			</vertex>
		</annotation>
		<center>
			<x>470.0</x>
			<y>416.0</y>
		</center>
	</part>
	<part>
		<name>2</name>
		<description>2</description>
		<color>#de21d5</color>
		<annotation>
			<vertex>
				<x>288.0</x>
				<y>379.0</y>
			</vertex>
			<vertex>
				<x>196.0</x>
				<y>367.0</y>
			</vertex>
			<vertex>
				<x>178.0</x>
				<y>420.0</y>
			</vertex>
			<vertex>
				<x>289.0</x>
				<y>443.0</y>
			</vertex>
			<vertex>
				<x>299.0</x>
				<y>380.0</y>
			</vertex>
		</annotation>
		<center>
			<x>300.0</x>
			<y>379.0</y>
		</center>
	</part>
	<part>
		<name>3</name>
		<description>3</description>
		<color>#c62f56</color>
		<annotation>
			<vertex>
				<x>212.0</x>
				<y>368.0</y>
			</vertex>
			<vertex>
				<x>199.0</x>
				<y>427.0</y>
			</vertex>
			<vertex>
				<x>102.0</x>
				<y>397.0</y>
			</vertex>
			<vertex>
				<x>110.0</x>
				<y>338.0</y>
			</vertex>
			<vertex>
				<x>188.0</x>
				<y>340.0</y>
			</vertex>
			<vertex>
				<x>211.0</x>
				<y>373.0</y>
			</vertex>
		</annotation>
		<center>
			<x>216.0</x>
			<y>372.0</y>
		</center>
	</part>
</parts>
